vindioai/__init__.py
vindioai/main.py
vindioai-0.2.4.dist-info/licenses/LICENSE
vindioai-0.2.4.dist-info/METADATA
vindioai-0.2.4.dist-info/WHEEL
vindioai-0.2.4.dist-info/top_level.txt
vindioai-0.2.4.dist-info/RECORD
