Metadata-Version: 2.4
Name: vindioai
Version: 0.2.4
Summary: Quantum Vision Theory in Deep Learning for Object Recognition
Home-page: https://github.com/vindioai/QVBlock
Author: Vindio AI Software Ltd. - Cem Direkoglu and Melike Sah
Author-email: vindioai@gmail.com
Classifier: Programming Language :: Python :: 3
Classifier: License :: OSI Approved :: GNU Affero General Public License v3
Classifier: Operating System :: OS Independent
Requires-Python: >=3.7
License-File: LICENSE
Requires-Dist: tensorflow>=2.0.0
Requires-Dist: numpy>=1.19.0
Dynamic: author
Dynamic: author-email
Dynamic: classifier
Dynamic: description
Dynamic: description-content-type
Dynamic: home-page
Dynamic: license-file
Dynamic: requires-dist
Dynamic: requires-python
Dynamic: summary
